{
    "bash command": {
        "basic info": "the note I took while coding with zsh/bash",
        "command": {
            "command name": [
                "rm",
                "cp",
                "ls",
                "find"
            ],
            "description": [
                "remove file",
                "copy file",
                "show files",
                "find certain files"
            ]
        }
    },
    "python new learnt method": {
        "module name": [
            "os",
            "json"
        ],
        "module new insight": [
            "os.path.exists()",
            "json.dump(dict, file, indent=4)"
        ]
    }
}